<?xml version="1.0" encoding="utf-8"?>
<EntityRelationships xmlns:xsi="http://www.w3.org/2001/XMLSchema-instance">
  <EntityRelationship Name="new_new_mp_interests_category_new_mp_interest">
    <EntityRelationshipType>OneToMany</EntityRelationshipType>
    <IsCustomizable>1</IsCustomizable>
    <IntroducedVersion>1.0</IntroducedVersion>
    <IsHierarchical>0</IsHierarchical>
    <ReferencingEntityName>new_mp_interests</ReferencingEntityName>
    <ReferencedEntityName>new_mp_interests_category</ReferencedEntityName>
    <CascadeAssign>NoCascade</CascadeAssign>
    <CascadeDelete>RemoveLink</CascadeDelete>
    <CascadeArchive>NoCascade</CascadeArchive>
    <CascadeReparent>NoCascade</CascadeReparent>
    <CascadeShare>NoCascade</CascadeShare>
    <CascadeUnshare>NoCascade</CascadeUnshare>
    <CascadeRollupView>NoCascade</CascadeRollupView>
    <IsValidForAdvancedFind>1</IsValidForAdvancedFind>
    <ReferencingAttributeName>new_CategoryId</ReferencingAttributeName>
    <RelationshipDescription>
      <Descriptions>
        <Description description="Unique identifier for MP_Interests_Category associated with MP_Interests." languagecode="1033" />
      </Descriptions>
    </RelationshipDescription>
    <EntityRelationshipRoles>
      <EntityRelationshipRole>
        <NavPaneDisplayOption>UseCollectionName</NavPaneDisplayOption>
        <NavPaneArea>Details</NavPaneArea>
        <NavPaneOrder>10000</NavPaneOrder>
        <NavigationPropertyName>new_CategoryId</NavigationPropertyName>
        <CustomLabels>
          <CustomLabel description="" languagecode="1033" />
        </CustomLabels>
        <RelationshipRoleType>1</RelationshipRoleType>
      </EntityRelationshipRole>
      <EntityRelationshipRole>
        <NavigationPropertyName>new_new_mp_interests_category_new_mp_interest</NavigationPropertyName>
        <RelationshipRoleType>0</RelationshipRoleType>
      </EntityRelationshipRole>
    </EntityRelationshipRoles>
  </EntityRelationship>
</EntityRelationships>