<?xml version="1.0" encoding="utf-8"?>
<savedqueries xmlns:xsi="http://www.w3.org/2001/XMLSchema-instance">
  <savedquery>
    <IsCustomizable>1</IsCustomizable>
    <CanBeDeleted>0</CanBeDeleted>
    <isquickfindquery>0</isquickfindquery>
    <isprivate>0</isprivate>
    <isdefault>1</isdefault>
    <savedqueryid>{1097cf3f-0e8e-46d6-95ad-7cce0b97fd00}</savedqueryid>
    <layoutxml>
      <grid name="resultset" jump="pia_name" select="1" icon="1" preview="1">
        <row name="result" id="pia_privacyimpactassessmentid">
          <cell name="pia_name" width="300" />
          <cell name="createdby" width="100" />
          <cell name="pia_team" width="100" />
          <cell name="createdon" width="125" />
        </row>
      </grid>
    </layoutxml>
    <querytype>0</querytype>
    <fetchxml>
      <fetch version="1.0" mapping="logical">
        <entity name="pia_privacyimpactassessment">
          <attribute name="pia_name" />
          <attribute name="createdon" />
          <order attribute="pia_name" descending="false" />
          <filter type="and">
            <condition attribute="statecode" operator="eq" value="0" />
          </filter>
          <attribute name="pia_team" />
          <attribute name="createdby" />
          <attribute name="pia_privacyimpactassessmentid" />
        </entity>
      </fetch>
    </fetchxml>
    <IntroducedVersion>1.0</IntroducedVersion>
    <LocalizedNames>
      <LocalizedName description="Active Privacy Impact Assessments" languagecode="1033" />
    </LocalizedNames>
  </savedquery>
</savedqueries>